[
  [
    {
      "id": "1A",
      "seatNo": "A1",
      "available": true
    },
    {
      "id": "1B",
      "custom": null,
      "seatNo": "A2",
      "available": true
    },
    {
      "id": "1C",
      "seatNo": "A3",
      "available": true
    },
    {
      "id": "1D",
      "seatNo": "A4",
      "available": true
    }
  ],
  [
    {
      "id": "2A",
      "seatNo": "B1",
      "available": true
    },
    {
      "id": "2B",
      "custom": null,
      "seatNo": "B2",
      "available": true
    },
    {
      "id": "2C",
      "seatNo": "B3",
      "available": true
    },
    {
      "id": "2D",
      "seatNo": "B4",
      "available": true
    }
  ],
  [
    {
      "id": "3A",
      "seatNo": "C1",
      "available": true
    },
    {
      "id": "3B",
      "custom": null,
      "seatNo": "C2",
      "available": true
    },
    {
      "id": "3C",
      "seatNo": "C3",
      "available": true
    },
    {
      "id": "3D",
      "seatNo": "C4",
      "available": true
    }
  ],
  [
    {
      "id": "4A",
      "seatNo": "D1",
      "available": true
    },
    {
      "id": "4B",
      "custom": null,
      "seatNo": "D2",
      "available": true
    },
    {
      "id": "4C",
      "seatNo": "D3",
      "available": true
    },
    {
      "id": "4D",
      "seatNo": "D4",
      "available": true
    }
  ],
  [
    {
      "id": "5A",
      "seatNo": "E1",
      "available": true
    },
    {
      "id": "5B",
      "custom": null,
      "seatNo": "E2",
      "available": true
    },
    {
      "id": "5C",
      "seatNo": "E3",
      "available": true
    },
    {
      "id": "5D",
      "seatNo": "E4",
      "available": true
    }
  ],
  [
    {
      "id": "6A",
      "seatNo": "F1",
      "available": true
    },
    {
      "id": "6B",
      "custom": null,
      "seatNo": "F2",
      "available": true
    },
    {
      "id": "6C",
      "seatNo": "E3",
      "available": true
    },
    {
      "id": "6D",
      "seatNo": "F4",
      "available": true
    }
  ],
  [
    {
      "id": "7A",
      "seatNo": "G1",
      "available": true
    },
    {
      "id": "7B",
      "custom": null,
      "seatNo": "G2",
      "available": true
    },
    {
      "id": "7C",
      "seatNo": "G3",
      "available": true
    },
    {
      "id": "7D",
      "seatNo": "G4",
      "available": true
    }
  ],
  [
    {
      "id": "8A",
      "seatNo": "H1",
      "available": true
    },
    {
      "id": "8B",
      "custom": null,
      "seatNo": "H2",
      "available": true
    },
    {
      "id": "8C",
      "seatNo": "H3",
      "available": true
    },
    {
      "id": "8D",
      "seatNo": "H4",
      "available": true
    }
  ],
  [
    {
      "id": "9A",
      "seatNo": "I1",
      "available": true
    },
    {
      "id": "9B",
      "custom": null,
      "seatNo": "I2",
      "available": true
    },
    {
      "id": "9C",
      "seatNo": "I3",
      "available": true
    },
    {
      "id": "9D",
      "seatNo": "I4",
      "available": true
    }
  ],
  [
    {
      "id": "10A",
      "seatNo": "J1",
      "available": true
    },
    {
      "id": "10B",
      "seatNo": "J2",
      "available": true
    },
    {
      "id": "10C",
      "seatNo": "J3",
      "available": true
    },
    {
      "id": "10D",
      "seatNo": "J4",
      "available": true
    },
    {
      "id": "10E",
      "seatNo": "J5",
      "available": true
    }
  ]
]